gym_unrealcv/__init__.py
gym_unrealcv/envs/__init__.py
gym_unrealcv/envs/base_env.py
gym_unrealcv/envs/navigation.py
gym_unrealcv/envs/rendezvous.py
gym_unrealcv/envs/rescue.py
gym_unrealcv/envs/track.py
gym_unrealcv/envs/agent/__init__.py
gym_unrealcv/envs/agent/character.py
gym_unrealcv/envs/setting/Navigation/Demo_Roof.json
gym_unrealcv/envs/setting/Navigation/SuburbNeighborhood_Day.json
gym_unrealcv/envs/setting/Navigation/SuburbNeighborhood_Night.json
gym_unrealcv/envs/setting/Track/ContainerYard_Day.json
gym_unrealcv/envs/setting/Track/ContainerYard_Night.json
gym_unrealcv/envs/setting/Track/Demo_Roof.json
gym_unrealcv/envs/setting/Track/Greek_Island.json
gym_unrealcv/envs/setting/Track/Map_ChemicalPlant_1.json
gym_unrealcv/envs/setting/Track/MiddleEast.json
gym_unrealcv/envs/setting/Track/Old_Town.json
gym_unrealcv/envs/setting/Track/SuburbNeighborhood_Day.json
gym_unrealcv/envs/setting/Track/SuburbNeighborhood_Night.json
gym_unrealcv/envs/setting/Track/track_train.json
gym_unrealcv/envs/tracking/baseline.py
gym_unrealcv/envs/tracking/interaction.py
gym_unrealcv/envs/tracking/reward.py
gym_unrealcv/envs/tracking/visualization.py
gym_unrealcv/envs/utils/misc.py
gym_unrealcv/envs/utils/reset_point.py
gym_unrealcv/envs/utils/reward.py
gym_unrealcv/envs/wrappers/__init__.py
gym_unrealcv/envs/wrappers/agents.py
gym_unrealcv/envs/wrappers/augmentation.py
gym_unrealcv/envs/wrappers/configUE.py
gym_unrealcv/envs/wrappers/early_done.py
gym_unrealcv/envs/wrappers/monitor.py
gym_unrealcv/envs/wrappers/time_dilation.py
gym_unrealcv-2.0.2.dist-info/METADATA
gym_unrealcv-2.0.2.dist-info/WHEEL
gym_unrealcv-2.0.2.dist-info/top_level.txt
gym_unrealcv-2.0.2.dist-info/RECORD
